[
    {
      "_id": "62bbafa72d142412c0cecb91",
      "name": "Afghanistan",
      "isActive": false,
      "code": "AF"
    },
    {
      "_id": "62bbafa72d142412c0cecb92",
      "name": "Åland Islands",
      "isActive": false,
      "code": "AX"
    },
    {
      "_id": "62bbafa72d142412c0cecb93",
      "name": "Albania",
      "isActive": false,
      "code": "AL"
    },
    {
      "_id": "62bbafa72d142412c0cecb94",
      "name": "Algeria",
      "isActive": false,
      "code": "DZ"
    },
    {
      "_id": "62bbafa72d142412c0cecb95",
      "name": "American Samoa",
      "isActive": false,
      "code": "AS"
    },
    {
      "_id": "62bbafa72d142412c0cecb96",
      "name": "AndorrA",
      "isActive": false,
      "code": "AD"
    },
    {
      "_id": "62bbafa72d142412c0cecb97",
      "name": "Angola",
      "isActive": false,
      "code": "AO"
    },
    {
      "_id": "62bbafa72d142412c0cecb98",
      "name": "Anguilla",
      "isActive": false,
      "code": "AI"
    },
    {
      "_id": "62bbafa72d142412c0cecb99",
      "name": "Antarctica",
      "isActive": false,
      "code": "AQ"
    },
    {
      "_id": "62bbafa72d142412c0cecb9a",
      "name": "Antigua and Barbuda",
      "isActive": false,
      "code": "AG"
    },
    {
      "_id": "62bbafa72d142412c0cecb9b",
      "name": "Argentina",
      "isActive": false,
      "code": "AR"
    },
    {
      "_id": "62bbafa72d142412c0cecb9c",
      "name": "Armenia",
      "isActive": false,
      "code": "AM"
    },
    {
      "_id": "62bbafa72d142412c0cecb9d",
      "name": "Aruba",
      "isActive": false,
      "code": "AW"
    },
    {
      "_id": "62bbafa72d142412c0cecb9e",
      "name": "Australia",
      "isActive": false,
      "code": "AU"
    },
    {
      "_id": "62bbafa72d142412c0cecb9f",
      "name": "Austria",
      "isActive": false,
      "code": "AT"
    },
    {
      "_id": "62bbafa72d142412c0cecba0",
      "name": "Azerbaijan",
      "isActive": false,
      "code": "AZ"
    },
    {
      "_id": "62bbafa72d142412c0cecba1",
      "name": "Bahamas",
      "isActive": false,
      "code": "BS"
    },
    {
      "_id": "62bbafa72d142412c0cecba2",
      "name": "Bahrain",
      "isActive": false,
      "code": "BH"
    },
    {
      "_id": "62bbafa72d142412c0cecba3",
      "name": "Bangladesh",
      "isActive": false,
      "code": "BD"
    },
    {
      "_id": "62bbafa72d142412c0cecba4",
      "name": "Barbados",
      "isActive": false,
      "code": "BB"
    },
    {
      "_id": "62bbafa72d142412c0cecba5",
      "name": "Belarus",
      "isActive": false,
      "code": "BY"
    },
    {
      "_id": "62bbafa72d142412c0cecba6",
      "name": "Belgium",
      "isActive": false,
      "code": "BE"
    },
    {
      "_id": "62bbafa72d142412c0cecba7",
      "name": "Belize",
      "isActive": false,
      "code": "BZ"
    },
    {
      "_id": "62bbafa72d142412c0cecba8",
      "name": "Benin",
      "isActive": false,
      "code": "BJ"
    },
    {
      "_id": "62bbafa72d142412c0cecba9",
      "name": "Bermuda",
      "isActive": false,
      "code": "BM"
    },
    {
      "_id": "62bbafa72d142412c0cecbaa",
      "name": "Bhutan",
      "isActive": false,
      "code": "BT"
    },
    {
      "_id": "62bbafa72d142412c0cecbab",
      "name": "Bolivia",
      "isActive": false,
      "code": "BO"
    },
    {
      "_id": "62bbafa72d142412c0cecbac",
      "name": "Bosnia and Herzegovina",
      "isActive": false,
      "code": "BA"
    },
    {
      "_id": "62bbafa72d142412c0cecbad",
      "name": "Botswana",
      "isActive": false,
      "code": "BW"
    },
    {
      "_id": "62bbafa72d142412c0cecbae",
      "name": "Bouvet Island",
      "isActive": false,
      "code": "BV"
    },
    {
      "_id": "62bbafa72d142412c0cecbaf",
      "name": "Brazil",
      "isActive": false,
      "code": "BR"
    },
    {
      "_id": "62bbafa72d142412c0cecbb0",
      "name": "British Indian Ocean Territory",
      "isActive": false,
      "code": "IO"
    },
    {
      "_id": "62bbafa72d142412c0cecbb1",
      "name": "Brunei Darussalam",
      "isActive": false,
      "code": "BN"
    },
    {
      "_id": "62bbafa72d142412c0cecbb2",
      "name": "Bulgaria",
      "isActive": false,
      "code": "BG"
    },
    {
      "_id": "62bbafa72d142412c0cecbb3",
      "name": "Burkina Faso",
      "isActive": false,
      "code": "BF"
    },
    {
      "_id": "62bbafa72d142412c0cecbb4",
      "name": "Burundi",
      "isActive": false,
      "code": "BI"
    },
    {
      "_id": "62bbafa72d142412c0cecbb5",
      "name": "Cambodia",
      "isActive": false,
      "code": "KH"
    },
    {
      "_id": "62bbafa72d142412c0cecbb6",
      "name": "Cameroon",
      "isActive": false,
      "code": "CM"
    },
    {
      "_id": "62bbafa72d142412c0cecbb7",
      "name": "Canada",
      "isActive": false,
      "code": "CA"
    },
    {
      "_id": "62bbafa72d142412c0cecbb8",
      "name": "Cape Verde",
      "isActive": false,
      "code": "CV"
    },
    {
      "_id": "62bbafa72d142412c0cecbb9",
      "name": "Cayman Islands",
      "isActive": false,
      "code": "KY"
    },
    {
      "_id": "62bbafa72d142412c0cecbba",
      "name": "Central African Republic",
      "isActive": false,
      "code": "CF"
    },
    {
      "_id": "62bbafa72d142412c0cecbbb",
      "name": "Chad",
      "isActive": false,
      "code": "TD"
    },
    {
      "_id": "62bbafa72d142412c0cecbbc",
      "name": "Chile",
      "isActive": false,
      "code": "CL"
    },
    {
      "_id": "62bbafa72d142412c0cecbbd",
      "name": "China",
      "isActive": false,
      "code": "CN"
    },
    {
      "_id": "62bbafa72d142412c0cecbbe",
      "name": "Christmas Island",
      "isActive": false,
      "code": "CX"
    },
    {
      "_id": "62bbafa72d142412c0cecbbf",
      "name": "Cocos (Keeling) Islands",
      "isActive": false,
      "code": "CC"
    },
    {
      "_id": "62bbafa72d142412c0cecbc0",
      "name": "Colombia",
      "isActive": false,
      "code": "CO"
    },
    {
      "_id": "62bbafa72d142412c0cecbc1",
      "name": "Comoros",
      "isActive": false,
      "code": "KM"
    },
    {
      "_id": "62bbafa72d142412c0cecbc2",
      "name": "Congo",
      "isActive": false,
      "code": "CG"
    },
    {
      "_id": "62bbafa72d142412c0cecbc3",
      "name": "Congo, The Democratic Republic of the",
      "isActive": false,
      "code": "CD"
    },
    {
      "_id": "62bbafa72d142412c0cecbc4",
      "name": "Cook Islands",
      "isActive": false,
      "code": "CK"
    },
    {
      "_id": "62bbafa72d142412c0cecbc5",
      "name": "Costa Rica",
      "isActive": false,
      "code": "CR"
    },
    {
      "_id": "62bbafa72d142412c0cecbc6",
      "name": "Cote D'Ivoire",
      "isActive": false,
      "code": "CI"
    },
    {
      "_id": "62bbafa72d142412c0cecbc7",
      "name": "Croatia",
      "isActive": false,
      "code": "HR"
    },
    {
      "_id": "62bbafa72d142412c0cecbc8",
      "name": "Cuba",
      "isActive": false,
      "code": "CU"
    },
    {
      "_id": "62bbafa72d142412c0cecbc9",
      "name": "Cyprus",
      "isActive": false,
      "code": "CY"
    },
    {
      "_id": "62bbafa72d142412c0cecbca",
      "name": "Czech Republic",
      "isActive": false,
      "code": "CZ"
    },
    {
      "_id": "62bbafa72d142412c0cecbcb",
      "name": "Denmark",
      "isActive": false,
      "code": "DK"
    },
    {
      "_id": "62bbafa72d142412c0cecbcc",
      "name": "Djibouti",
      "isActive": false,
      "code": "DJ"
    },
    {
      "_id": "62bbafa72d142412c0cecbcd",
      "name": "Dominica",
      "isActive": false,
      "code": "DM"
    },
    {
      "_id": "62bbafa72d142412c0cecbce",
      "name": "Dominican Republic",
      "isActive": false,
      "code": "DO"
    },
    {
      "_id": "62bbafa72d142412c0cecbcf",
      "name": "Ecuador",
      "isActive": false,
      "code": "EC"
    },
    {
      "_id": "62bbafa72d142412c0cecbd0",
      "name": "Egypt",
      "isActive": false,
      "code": "EG"
    },
    {
      "_id": "62bbafa72d142412c0cecbd1",
      "name": "El Salvador",
      "isActive": false,
      "code": "SV"
    },
    {
      "_id": "62bbafa72d142412c0cecbd2",
      "name": "Equatorial Guinea",
      "isActive": false,
      "code": "GQ"
    },
    {
      "_id": "62bbafa72d142412c0cecbd3",
      "name": "Eritrea",
      "isActive": false,
      "code": "ER"
    },
    {
      "_id": "62bbafa72d142412c0cecbd4",
      "name": "Estonia",
      "isActive": false,
      "code": "EE"
    },
    {
      "_id": "62bbafa72d142412c0cecbd5",
      "name": "Ethiopia",
      "isActive": false,
      "code": "ET"
    },
    {
      "_id": "62bbafa72d142412c0cecbd6",
      "name": "Falkland Islands (Malvinas)",
      "isActive": false,
      "code": "FK"
    },
    {
      "_id": "62bbafa72d142412c0cecbd7",
      "name": "Faroe Islands",
      "isActive": false,
      "code": "FO"
    },
    {
      "_id": "62bbafa72d142412c0cecbd8",
      "name": "Fiji",
      "isActive": false,
      "code": "FJ"
    },
    {
      "_id": "62bbafa72d142412c0cecbd9",
      "name": "Finland",
      "isActive": false,
      "code": "FI"
    },
    {
      "_id": "62bbafa72d142412c0cecbda",
      "name": "France",
      "isActive": false,
      "code": "FR"
    },
    {
      "_id": "62bbafa72d142412c0cecbdb",
      "name": "French Guiana",
      "isActive": false,
      "code": "GF"
    },
    {
      "_id": "62bbafa72d142412c0cecbdc",
      "name": "French Polynesia",
      "isActive": false,
      "code": "PF"
    },
    {
      "_id": "62bbafa72d142412c0cecbdd",
      "name": "French Southern Territories",
      "isActive": false,
      "code": "TF"
    },
    {
      "_id": "62bbafa72d142412c0cecbde",
      "name": "Gabon",
      "isActive": false,
      "code": "GA"
    },
    {
      "_id": "62bbafa72d142412c0cecbdf",
      "name": "Gambia",
      "isActive": false,
      "code": "GM"
    },
    {
      "_id": "62bbafa72d142412c0cecbe0",
      "name": "Georgia",
      "isActive": false,
      "code": "GE"
    },
    {
      "_id": "62bbafa72d142412c0cecbe1",
      "name": "Germany",
      "isActive": false,
      "code": "DE"
    },
    {
      "_id": "62bbafa72d142412c0cecbe2",
      "name": "Ghana",
      "isActive": false,
      "code": "GH"
    },
    {
      "_id": "62bbafa72d142412c0cecbe3",
      "name": "Gibraltar",
      "isActive": false,
      "code": "GI"
    },
    {
      "_id": "62bbafa72d142412c0cecbe4",
      "name": "Greece",
      "isActive": false,
      "code": "GR"
    },
    {
      "_id": "62bbafa72d142412c0cecbe5",
      "name": "Greenland",
      "isActive": false,
      "code": "GL"
    },
    {
      "_id": "62bbafa72d142412c0cecbe6",
      "name": "Grenada",
      "isActive": false,
      "code": "GD"
    },
    {
      "_id": "62bbafa72d142412c0cecbe7",
      "name": "Guadeloupe",
      "isActive": false,
      "code": "GP"
    },
    {
      "_id": "62bbafa72d142412c0cecbe8",
      "name": "Guam",
      "isActive": false,
      "code": "GU"
    },
    {
      "_id": "62bbafa72d142412c0cecbe9",
      "name": "Guatemala",
      "isActive": false,
      "code": "GT"
    },
    {
      "_id": "62bbafa72d142412c0cecbea",
      "name": "Guernsey",
      "isActive": false,
      "code": "GG"
    },
    {
      "_id": "62bbafa72d142412c0cecbeb",
      "name": "Guinea",
      "isActive": false,
      "code": "GN"
    },
    {
      "_id": "62bbafa72d142412c0cecbec",
      "name": "Guinea-Bissau",
      "isActive": false,
      "code": "GW"
    },
    {
      "_id": "62bbafa72d142412c0cecbed",
      "name": "Guyana",
      "isActive": false,
      "code": "GY"
    },
    {
      "_id": "62bbafa72d142412c0cecbee",
      "name": "Haiti",
      "isActive": false,
      "code": "HT"
    },
    {
      "_id": "62bbafa72d142412c0cecbef",
      "name": "Heard Island and Mcdonald Islands",
      "isActive": false,
      "code": "HM"
    },
    {
      "_id": "62bbafa72d142412c0cecbf0",
      "name": "Holy See (Vatican City State)",
      "isActive": false,
      "code": "VA"
    },
    {
      "_id": "62bbafa72d142412c0cecbf1",
      "name": "Honduras",
      "isActive": false,
      "code": "HN"
    },
    {
      "_id": "62bbafa72d142412c0cecbf2",
      "name": "Hong Kong",
      "isActive": false,
      "code": "HK"
    },
    {
      "_id": "62bbafa72d142412c0cecbf3",
      "name": "Hungary",
      "isActive": false,
      "code": "HU"
    },
    {
      "_id": "62bbafa72d142412c0cecbf4",
      "name": "Iceland",
      "isActive": false,
      "code": "IS"
    },
    {
      "_id": "62bbafa72d142412c0cecbf5",
      "name": "India",
      "isActive": false,
      "code": "IN"
    },
    {
      "_id": "62bbafa72d142412c0cecbf6",
      "name": "Indonesia",
      "isActive": false,
      "code": "ID"
    },
    {
      "_id": "62bbafa72d142412c0cecbf7",
      "name": "Iran, Islamic Republic Of",
      "isActive": false,
      "code": "IR"
    },
    {
      "_id": "62bbafa72d142412c0cecbf8",
      "name": "Iraq",
      "isActive": false,
      "code": "IQ"
    },
    {
      "_id": "62bbafa72d142412c0cecbf9",
      "name": "Ireland",
      "isActive": false,
      "code": "IE"
    },
    {
      "_id": "62bbafa72d142412c0cecbfa",
      "name": "Isle of Man",
      "isActive": false,
      "code": "IM"
    },
    {
      "_id": "62bbafa72d142412c0cecbfb",
      "name": "Israel",
      "isActive": false,
      "code": "IL"
    },
    {
      "_id": "62bbafa72d142412c0cecbfc",
      "name": "Italy",
      "isActive": false,
      "code": "IT"
    },
    {
      "_id": "62bbafa72d142412c0cecbfd",
      "name": "Jamaica",
      "isActive": false,
      "code": "JM"
    },
    {
      "_id": "62bbafa72d142412c0cecbfe",
      "name": "Japan",
      "isActive": false,
      "code": "JP"
    },
    {
      "_id": "62bbafa72d142412c0cecbff",
      "name": "Jersey",
      "isActive": false,
      "code": "JE"
    },
    {
      "_id": "62bbafa72d142412c0cecc00",
      "name": "Jordan",
      "isActive": false,
      "code": "JO"
    },
    {
      "_id": "62bbafa72d142412c0cecc01",
      "name": "Kazakhstan",
      "isActive": false,
      "code": "KZ"
    },
    {
      "_id": "62bbafa72d142412c0cecc02",
      "name": "Kenya",
      "isActive": false,
      "code": "KE"
    },
    {
      "_id": "62bbafa72d142412c0cecc03",
      "name": "Kiribati",
      "isActive": false,
      "code": "KI"
    },
    {
      "_id": "62bbafa72d142412c0cecc04",
      "name": "Korea, Democratic People'S Republic of",
      "isActive": false,
      "code": "KP"
    },
    {
      "_id": "62bbafa72d142412c0cecc05",
      "name": "Korea, Republic of",
      "isActive": false,
      "code": "KR"
    },
    {
      "_id": "62bbafa72d142412c0cecc06",
      "name": "Kuwait",
      "isActive": false,
      "code": "KW"
    },
    {
      "_id": "62bbafa72d142412c0cecc07",
      "name": "Kyrgyzstan",
      "isActive": false,
      "code": "KG"
    },
    {
      "_id": "62bbafa72d142412c0cecc08",
      "name": "Lao People'S Democratic Republic",
      "isActive": false,
      "code": "LA"
    },
    {
      "_id": "62bbafa72d142412c0cecc09",
      "name": "Latvia",
      "isActive": false,
      "code": "LV"
    },
    {
      "_id": "62bbafa72d142412c0cecc0a",
      "name": "Lebanon",
      "isActive": false,
      "code": "LB"
    },
    {
      "_id": "62bbafa72d142412c0cecc0b",
      "name": "Lesotho",
      "isActive": false,
      "code": "LS"
    },
    {
      "_id": "62bbafa72d142412c0cecc0c",
      "name": "Liberia",
      "isActive": false,
      "code": "LR"
    },
    {
      "_id": "62bbafa72d142412c0cecc0d",
      "name": "Libyan Arab Jamahiriya",
      "isActive": false,
      "code": "LY"
    },
    {
      "_id": "62bbafa72d142412c0cecc0e",
      "name": "Liechtenstein",
      "isActive": false,
      "code": "LI"
    },
    {
      "_id": "62bbafa72d142412c0cecc0f",
      "name": "Lithuania",
      "isActive": false,
      "code": "LT"
    },
    {
      "_id": "62bbafa72d142412c0cecc10",
      "name": "Luxembourg",
      "isActive": false,
      "code": "LU"
    },
    {
      "_id": "62bbafa72d142412c0cecc11",
      "name": "Macao",
      "isActive": false,
      "code": "MO"
    },
    {
      "_id": "62bbafa72d142412c0cecc12",
      "name": "Macedonia, The Former Yugoslav Republic of",
      "isActive": false,
      "code": "MK"
    },
    {
      "_id": "62bbafa72d142412c0cecc13",
      "name": "Madagascar",
      "isActive": false,
      "code": "MG"
    },
    {
      "_id": "62bbafa72d142412c0cecc14",
      "name": "Malawi",
      "isActive": false,
      "code": "MW"
    },
    {
      "_id": "62bbafa72d142412c0cecc15",
      "name": "Malaysia",
      "isActive": false,
      "code": "MY"
    },
    {
      "_id": "62bbafa72d142412c0cecc16",
      "name": "Maldives",
      "isActive": false,
      "code": "MV"
    },
    {
      "_id": "62bbafa72d142412c0cecc17",
      "name": "Mali",
      "isActive": false,
      "code": "ML"
    },
    {
      "_id": "62bbafa72d142412c0cecc18",
      "name": "Malta",
      "isActive": false,
      "code": "MT"
    },
    {
      "_id": "62bbafa72d142412c0cecc19",
      "name": "Marshall Islands",
      "isActive": false,
      "code": "MH"
    },
    {
      "_id": "62bbafa72d142412c0cecc1a",
      "name": "Martinique",
      "isActive": false,
      "code": "MQ"
    },
    {
      "_id": "62bbafa72d142412c0cecc1b",
      "name": "Mauritania",
      "isActive": false,
      "code": "MR"
    },
    {
      "_id": "62bbafa72d142412c0cecc1c",
      "name": "Mauritius",
      "isActive": false,
      "code": "MU"
    },
    {
      "_id": "62bbafa72d142412c0cecc1d",
      "name": "Mayotte",
      "isActive": false,
      "code": "YT"
    },
    {
      "_id": "62bbafa72d142412c0cecc1e",
      "name": "Mexico",
      "isActive": false,
      "code": "MX"
    },
    {
      "_id": "62bbafa72d142412c0cecc1f",
      "name": "Micronesia, Federated States of",
      "isActive": false,
      "code": "FM"
    },
    {
      "_id": "62bbafa72d142412c0cecc20",
      "name": "Moldova, Republic of",
      "isActive": false,
      "code": "MD"
    },
    {
      "_id": "62bbafa72d142412c0cecc21",
      "name": "Monaco",
      "isActive": false,
      "code": "MC"
    },
    {
      "_id": "62bbafa72d142412c0cecc22",
      "name": "Mongolia",
      "isActive": false,
      "code": "MN"
    },
    {
      "_id": "62bbafa72d142412c0cecc23",
      "name": "Montserrat",
      "isActive": false,
      "code": "MS"
    },
    {
      "_id": "62bbafa72d142412c0cecc24",
      "name": "Morocco",
      "isActive": false,
      "code": "MA"
    },
    {
      "_id": "62bbafa72d142412c0cecc25",
      "name": "Mozambique",
      "isActive": false,
      "code": "MZ"
    },
    {
      "_id": "62bbafa72d142412c0cecc26",
      "name": "Myanmar",
      "isActive": false,
      "code": "MM"
    },
    {
      "_id": "62bbafa72d142412c0cecc27",
      "name": "Namibia",
      "isActive": false,
      "code": "NA"
    },
    {
      "_id": "62bbafa72d142412c0cecc28",
      "name": "Nauru",
      "isActive": false,
      "code": "NR"
    },
    {
      "_id": "62bbafa72d142412c0cecc29",
      "name": "Nepal",
      "isActive": false,
      "code": "NP"
    },
    {
      "_id": "62bbafa72d142412c0cecc2a",
      "name": "Netherlands",
      "isActive": false,
      "code": "NL"
    },
    {
      "_id": "62bbafa72d142412c0cecc2b",
      "name": "Netherlands Antilles",
      "isActive": false,
      "code": "AN"
    },
    {
      "_id": "62bbafa72d142412c0cecc2c",
      "name": "New Caledonia",
      "isActive": false,
      "code": "NC"
    },
    {
      "_id": "62bbafa72d142412c0cecc2d",
      "name": "New Zealand",
      "isActive": false,
      "code": "NZ"
    },
    {
      "_id": "62bbafa72d142412c0cecc2e",
      "name": "Nicaragua",
      "isActive": false,
      "code": "NI"
    },
    {
      "_id": "62bbafa72d142412c0cecc2f",
      "name": "Niger",
      "isActive": false,
      "code": "NE"
    },
    {
      "_id": "62bbafa72d142412c0cecc30",
      "name": "Nigeria",
      "isActive": true,
      "code": "NG"
    },
    {
      "_id": "62bbafa72d142412c0cecc31",
      "name": "Niue",
      "isActive": false,
      "code": "NU"
    },
    {
      "_id": "62bbafa72d142412c0cecc32",
      "name": "Norfolk Island",
      "isActive": false,
      "code": "NF"
    },
    {
      "_id": "62bbafa72d142412c0cecc33",
      "name": "Northern Mariana Islands",
      "isActive": false,
      "code": "MP"
    },
    {
      "_id": "62bbafa72d142412c0cecc34",
      "name": "Norway",
      "isActive": false,
      "code": "NO"
    },
    {
      "_id": "62bbafa72d142412c0cecc35",
      "name": "Oman",
      "isActive": false,
      "code": "OM"
    },
    {
      "_id": "62bbafa72d142412c0cecc36",
      "name": "Pakistan",
      "isActive": false,
      "code": "PK"
    },
    {
      "_id": "62bbafa72d142412c0cecc37",
      "name": "Palau",
      "isActive": false,
      "code": "PW"
    },
    {
      "_id": "62bbafa72d142412c0cecc38",
      "name": "Palestinian Territory, Occupied",
      "isActive": false,
      "code": "PS"
    },
    {
      "_id": "62bbafa72d142412c0cecc39",
      "name": "Panama",
      "isActive": false,
      "code": "PA"
    },
    {
      "_id": "62bbafa72d142412c0cecc3a",
      "name": "Papua New Guinea",
      "isActive": false,
      "code": "PG"
    },
    {
      "_id": "62bbafa72d142412c0cecc3b",
      "name": "Paraguay",
      "isActive": false,
      "code": "PY"
    },
    {
      "_id": "62bbafa72d142412c0cecc3c",
      "name": "Peru",
      "isActive": false,
      "code": "PE"
    },
    {
      "_id": "62bbafa72d142412c0cecc3d",
      "name": "Philippines",
      "isActive": false,
      "code": "PH"
    },
    {
      "_id": "62bbafa72d142412c0cecc3e",
      "name": "Pitcairn",
      "isActive": false,
      "code": "PN"
    },
    {
      "_id": "62bbafa72d142412c0cecc3f",
      "name": "Poland",
      "isActive": false,
      "code": "PL"
    },
    {
      "_id": "62bbafa72d142412c0cecc40",
      "name": "Portugal",
      "isActive": false,
      "code": "PT"
    },
    {
      "_id": "62bbafa72d142412c0cecc41",
      "name": "Puerto Rico",
      "isActive": false,
      "code": "PR"
    },
    {
      "_id": "62bbafa72d142412c0cecc42",
      "name": "Qatar",
      "isActive": false,
      "code": "QA"
    },
    {
      "_id": "62bbafa72d142412c0cecc43",
      "name": "Reunion",
      "isActive": false,
      "code": "RE"
    },
    {
      "_id": "62bbafa72d142412c0cecc44",
      "name": "Romania",
      "isActive": false,
      "code": "RO"
    },
    {
      "_id": "62bbafa72d142412c0cecc45",
      "name": "Russian Federation",
      "isActive": false,
      "code": "RU"
    },
    {
      "_id": "62bbafa72d142412c0cecc46",
      "name": "RWANDA",
      "isActive": false,
      "code": "RW"
    },
    {
      "_id": "62bbafa72d142412c0cecc47",
      "name": "Saint Helena",
      "isActive": false,
      "code": "SH"
    },
    {
      "_id": "62bbafa72d142412c0cecc48",
      "name": "Saint Kitts and Nevis",
      "isActive": false,
      "code": "KN"
    },
    {
      "_id": "62bbafa72d142412c0cecc49",
      "name": "Saint Lucia",
      "isActive": false,
      "code": "LC"
    },
    {
      "_id": "62bbafa72d142412c0cecc4a",
      "name": "Saint Pierre and Miquelon",
      "isActive": false,
      "code": "PM"
    },
    {
      "_id": "62bbafa72d142412c0cecc4b",
      "name": "Saint Vincent and the Grenadines",
      "isActive": false,
      "code": "VC"
    },
    {
      "_id": "62bbafa72d142412c0cecc4c",
      "name": "Samoa",
      "isActive": false,
      "code": "WS"
    },
    {
      "_id": "62bbafa72d142412c0cecc4d",
      "name": "San Marino",
      "isActive": false,
      "code": "SM"
    },
    {
      "_id": "62bbafa72d142412c0cecc4e",
      "name": "Sao Tome and Principe",
      "isActive": false,
      "code": "ST"
    },
    {
      "_id": "62bbafa72d142412c0cecc4f",
      "name": "Saudi Arabia",
      "isActive": false,
      "code": "SA"
    },
    {
      "_id": "62bbafa72d142412c0cecc50",
      "name": "Senegal",
      "isActive": false,
      "code": "SN"
    },
    {
      "_id": "62bbafa72d142412c0cecc51",
      "name": "Serbia and Montenegro",
      "isActive": false,
      "code": "CS"
    },
    {
      "_id": "62bbafa72d142412c0cecc52",
      "name": "Seychelles",
      "isActive": false,
      "code": "SC"
    },
    {
      "_id": "62bbafa72d142412c0cecc53",
      "name": "Sierra Leone",
      "isActive": false,
      "code": "SL"
    },
    {
      "_id": "62bbafa72d142412c0cecc54",
      "name": "Singapore",
      "isActive": false,
      "code": "SG"
    },
    {
      "_id": "62bbafa72d142412c0cecc55",
      "name": "Slovakia",
      "isActive": false,
      "code": "SK"
    },
    {
      "_id": "62bbafa72d142412c0cecc56",
      "name": "Slovenia",
      "isActive": false,
      "code": "SI"
    },
    {
      "_id": "62bbafa72d142412c0cecc57",
      "name": "Solomon Islands",
      "isActive": false,
      "code": "SB"
    },
    {
      "_id": "62bbafa72d142412c0cecc58",
      "name": "Somalia",
      "isActive": false,
      "code": "SO"
    },
    {
      "_id": "62bbafa72d142412c0cecc59",
      "name": "South Africa",
      "isActive": false,
      "code": "ZA"
    },
    {
      "_id": "62bbafa72d142412c0cecc5a",
      "name": "South Georgia and the South Sandwich Islands",
      "isActive": false,
      "code": "GS"
    },
    {
      "_id": "62bbafa72d142412c0cecc5b",
      "name": "Spain",
      "isActive": false,
      "code": "ES"
    },
    {
      "_id": "62bbafa72d142412c0cecc5c",
      "name": "Sri Lanka",
      "isActive": false,
      "code": "LK"
    },
    {
      "_id": "62bbafa72d142412c0cecc5d",
      "name": "Sudan",
      "isActive": false,
      "code": "SD"
    },
    {
      "_id": "62bbafa72d142412c0cecc5e",
      "name": "Suriname",
      "isActive": false,
      "code": "SR"
    },
    {
      "_id": "62bbafa72d142412c0cecc5f",
      "name": "Svalbard and Jan Mayen",
      "isActive": false,
      "code": "SJ"
    },
    {
      "_id": "62bbafa72d142412c0cecc60",
      "name": "Swaziland",
      "isActive": false,
      "code": "SZ"
    },
    {
      "_id": "62bbafa72d142412c0cecc61",
      "name": "Sweden",
      "isActive": false,
      "code": "SE"
    },
    {
      "_id": "62bbafa72d142412c0cecc62",
      "name": "Switzerland",
      "isActive": false,
      "code": "CH"
    },
    {
      "_id": "62bbafa72d142412c0cecc63",
      "name": "Syrian Arab Republic",
      "isActive": false,
      "code": "SY"
    },
    {
      "_id": "62bbafa72d142412c0cecc64",
      "name": "Taiwan, Province of China",
      "isActive": false,
      "code": "TW"
    },
    {
      "_id": "62bbafa72d142412c0cecc65",
      "name": "Tajikistan",
      "isActive": false,
      "code": "TJ"
    },
    {
      "_id": "62bbafa72d142412c0cecc66",
      "name": "Tanzania, United Republic of",
      "isActive": false,
      "code": "TZ"
    },
    {
      "_id": "62bbafa72d142412c0cecc67",
      "name": "Thailand",
      "isActive": false,
      "code": "TH"
    },
    {
      "_id": "62bbafa72d142412c0cecc68",
      "name": "Timor-Leste",
      "isActive": false,
      "code": "TL"
    },
    {
      "_id": "62bbafa72d142412c0cecc69",
      "name": "Togo",
      "isActive": false,
      "code": "TG"
    },
    {
      "_id": "62bbafa72d142412c0cecc6a",
      "name": "Tokelau",
      "isActive": false,
      "code": "TK"
    },
    {
      "_id": "62bbafa72d142412c0cecc6b",
      "name": "Tonga",
      "isActive": false,
      "code": "TO"
    },
    {
      "_id": "62bbafa72d142412c0cecc6c",
      "name": "Trinidad and Tobago",
      "isActive": false,
      "code": "TT"
    },
    {
      "_id": "62bbafa72d142412c0cecc6d",
      "name": "Tunisia",
      "isActive": false,
      "code": "TN"
    },
    {
      "_id": "62bbafa72d142412c0cecc6e",
      "name": "Turkey",
      "isActive": false,
      "code": "TR"
    },
    {
      "_id": "62bbafa72d142412c0cecc6f",
      "name": "Turkmenistan",
      "isActive": false,
      "code": "TM"
    },
    {
      "_id": "62bbafa72d142412c0cecc70",
      "name": "Turks and Caicos Islands",
      "isActive": false,
      "code": "TC"
    },
    {
      "_id": "62bbafa72d142412c0cecc71",
      "name": "Tuvalu",
      "isActive": false,
      "code": "TV"
    },
    {
      "_id": "62bbafa72d142412c0cecc72",
      "name": "Uganda",
      "isActive": false,
      "code": "UG"
    },
    {
      "_id": "62bbafa72d142412c0cecc73",
      "name": "Ukraine",
      "isActive": false,
      "code": "UA"
    },
    {
      "_id": "62bbafa72d142412c0cecc74",
      "name": "United Arab Emirates",
      "isActive": false,
      "code": "AE"
    },
    {
      "_id": "62bbafa72d142412c0cecc75",
      "name": "United Kingdom",
      "isActive": false,
      "code": "GB"
    },
    {
      "_id": "62bbafa72d142412c0cecc76",
      "name": "United States",
      "isActive": false,
      "code": "US"
    },
    {
      "_id": "62bbafa72d142412c0cecc77",
      "name": "United States Minor Outlying Islands",
      "isActive": false,
      "code": "UM"
    },
    {
      "_id": "62bbafa72d142412c0cecc78",
      "name": "Uruguay",
      "isActive": false,
      "code": "UY"
    },
    {
      "_id": "62bbafa72d142412c0cecc79",
      "name": "Uzbekistan",
      "isActive": false,
      "code": "UZ"
    },
    {
      "_id": "62bbafa72d142412c0cecc7a",
      "name": "Vanuatu",
      "isActive": false,
      "code": "VU"
    },
    {
      "_id": "62bbafa72d142412c0cecc7b",
      "name": "Venezuela",
      "isActive": false,
      "code": "VE"
    },
    {
      "_id": "62bbafa72d142412c0cecc7c",
      "name": "Viet Nam",
      "isActive": false,
      "code": "VN"
    },
    {
      "_id": "62bbafa72d142412c0cecc7d",
      "name": "Virgin Islands, British",
      "isActive": false,
      "code": "VG"
    },
    {
      "_id": "62bbafa72d142412c0cecc7e",
      "name": "Virgin Islands, U.S.",
      "isActive": false,
      "code": "VI"
    },
    {
      "_id": "62bbafa72d142412c0cecc7f",
      "name": "Wallis and Futuna",
      "isActive": false,
      "code": "WF"
    },
    {
      "_id": "62bbafa72d142412c0cecc80",
      "name": "Western Sahara",
      "isActive": false,
      "code": "EH"
    },
    {
      "_id": "62bbafa72d142412c0cecc81",
      "name": "Yemen",
      "isActive": false,
      "code": "YE"
    },
    {
      "_id": "62bbafa72d142412c0cecc82",
      "name": "Zambia",
      "isActive": false,
      "code": "ZM"
    },
    {
      "_id": "62bbafa72d142412c0cecc83",
      "name": "Zimbabwe",
      "isActive": false,
      "code": "ZW"
    }
  ]